{
  "D5": "LED_SMD:LED_0603_1608Metric",
  "D7": "LED_SMD:LED_0603_1608Metric",
  "D9": "LED_SMD:LED_0603_1608Metric",
  "D11": "LED_SMD:LED_0603_1608Metric",
  "D12": "LED_SMD:LED_0603_1608Metric",
  "D1": "Resistor_SMD:R_1206",
  "D2": "Resistor_SMD:R_0603",
  "D3": "Resistor_SMD:R_0603",
  "D4": "Resistor_SMD:R_0603",
  "D6": "Resistor_SMD:R_1206",
  "D8": "Resistor_SMD:R_1206",
  "D10": "Resistor_SMD:R_1206",
  "Q1": "TO_SOT_Packages_SMD:SOT-23",
  "Q2": "TO_SOT_Packages_SMD:SOT-23",
  "Q3": "TO_SOT_Packages_SMD:SOT-23",
  "U6": "Package_SO:SOIC-8_5.23x5.23mm_P1.27mm"
}
